src/logphy/ShiftReg_3d.sv
module ShiftReg_3d #(
    parameter DATA_BIT_WIDTH = 3
)(
    input   clk,
    input   reset,
    input   enable,
    output  enable_ack,
    output  valid_o,
    input   [DATA_BIT_WIDTH-1:0] d_i,
    output  [DATA_BIT_WIDTH-1:0] q_o
);
    // Compile-time error detection
    initial begin
        if (DATA_BIT_WIDTH == 1) begin
            $error("DATA_BIT_WIDTH must be greater than 1 for proper operation.");
        end
    end

    reg [DATA_BIT_WIDTH-1:0] sync_r [2:0];
    assign q_o = sync_r[2];

    reg enable_ack_r;
    assign enable_ack = enable_ack_r;

    // Add a single shift register for valid_o
    reg [2:0] valid_r;
    assign valid_o = valid_r[2];

    // Asynchronous reset
    always @(posedge clk or reset) begin
        if (reset) begin
            sync_r[0] <= {DATA_BIT_WIDTH{1'b0}};
            sync_r[1] <= {DATA_BIT_WIDTH{1'b0}};
            sync_r[2] <= {DATA_BIT_WIDTH{1'b0}};
            valid_r[0] <= 1'b0;
            valid_r[1] <= 1'b0;
            valid_r[2] <= 1'b0;
        end else begin
            if (enable) begin
                sync_r[0] <= d_i;
                valid_r[0] <= 1'b1; // Set valid when enable is high
                enable_ack_r <= 1'b1;
            end else begin
                sync_r[0] <= sync_r[0];
                enable_ack_r <= 1'b0;
                valid_r[0] <= 1'b0; // Clear valid when enable is low
            end
            sync_r[1] <= sync_r[0];
            sync_r[2] <= sync_r[1];
            valid_r[1] <= valid_r[0];
            valid_r[2] <= valid_r[1];
            
        end
    end
endmodule

tb/logphy/ShiftReg_3d_tb.sv
`timescale 1ps/1ps

module ShiftReg_3d_tb;

    // Parameters
    parameter DATA_BIT_WIDTH = 8;

    // Testbench signals
    reg clk;
    reg reset;
    reg enable;
    reg [DATA_BIT_WIDTH-1:0] d_i;
    wire [DATA_BIT_WIDTH-1:0] q_o;
    wire enable_ack;
    wire valid_o;

    // Instantiate the ShiftReg_3d module
    ShiftReg_3d #(
        .DATA_BIT_WIDTH(DATA_BIT_WIDTH)
    ) uut (
        .clk(clk),
        .reset(reset),
        .enable(enable),
        .enable_ack(enable_ack),
        .valid_o(valid_o),
        .d_i(d_i),
        .q_o(q_o)
    );

    initial begin
        $dumpfile("../ShiftReg_3d_tb.vcd");
        $dumpvars(0, ShiftReg_3d_tb);
    end

    // Clock generation
    initial begin
        clk = 0;
        forever #5 clk = ~clk; // 10ns clock period
    end

    // Test sequence
    initial begin
        // Initialize signals
        reset = 1;
        enable = 0;
        d_i = 0;

        // Apply reset
        #20;
        reset = 0;

        // Test case 1: Shift data through the register
        #10;
        enable = 1;
        d_i = 8'b10101010; // Input data
        #10;
        enable = 0;

        // Wait for data to propagate through the shift register
        #30;

        // Test case 2: Shift new data
        enable = 1;
        d_i = 8'b01100110; // New input data
        #10;
        enable = 0;

        // Wait for data to propagate
        #30;

        // Test case 3: Reset the module
        reset = 1;
        #10;
        reset = 0;

        // End simulation
        #50;
        $finish;
    end

    // Monitor outputs

endmodule

tb/Sim_results/ShiftReg_3d_tb.vcd
$version Generated by VerilatedVcd $end
$timescale 1ps $end
 $scope module TOP $end
  $scope module ShiftReg_3d_tb $end
   $var wire 32 0 DATA_BIT_WIDTH [31:0] $end
   $var wire 1 , clk $end
   $var wire 1 - reset $end
   $var wire 1 . enable $end
   $var wire 8 / d_i [7:0] $end
   $var wire 8 # q_o [7:0] $end
   $var wire 1 $ enable_ack $end
   $var wire 1 % valid_o $end
   $scope module uut $end
    $var wire 32 0 DATA_BIT_WIDTH [31:0] $end
    $var wire 1 , clk $end
    $var wire 1 - reset $end
    $var wire 1 . enable $end
    $var wire 1 $ enable_ack $end
    $var wire 1 % valid_o $end
    $var wire 8 / d_i [7:0] $end
    $var wire 8 # q_o [7:0] $end
    $var wire 8 & sync_r[0] [7:0] $end
    $var wire 8 ' sync_r[1] [7:0] $end
    $var wire 8 ( sync_r[2] [7:0] $end
    $var wire 1 $ enable_ack_r $end
    $var wire 1 ) valid_r[0] $end
    $var wire 1 * valid_r[1] $end
    $var wire 1 + valid_r[2] $end
   $upscope $end
  $upscope $end
 $upscope $end
$enddefinitions $end


#0
b00000000 #
0$
0%
b00000000 &
b00000000 '
b00000000 (
0)
0*
0+
0,
1-
0.
b00000000 /
b00000000000000000000000000001000 0
#5
1,
#10
0,
#15
1,
#20
0,
0-
#25
1,
#30
0,
1.
b10101010 /
#35
1$
b10101010 &
1)
1,
#40
0,
0.
#45
0$
b10101010 '
0)
1*
1,
#50
0,
#55
b10101010 #
1%
b10101010 (
0*
1+
1,
#60
0,
#65
0%
0+
1,
#70
0,
1.
b01100110 /
#75
1$
b01100110 &
1)
1,
#80
0,
0.
#85
0$
b01100110 '
0)
1*
1,
#90
0,
#95
b01100110 #
1%
b01100110 (
0*
1+
1,
#100
0,
#105
0%
0+
1,
#110
b00000000 #
b00000000 &
b00000000 '
b00000000 (
0,
1-
#115
1,
#120
0,
0-
